LICENSE
README.md
setup.cfg
setup.py
RegexCap.egg-info/PKG-INFO
RegexCap.egg-info/SOURCES.txt
RegexCap.egg-info/dependency_links.txt
RegexCap.egg-info/entry_points.txt
RegexCap.egg-info/top_level.txt
src/__init__.py
src/regexcap.py