Metadata-Version: 2.1
Name: RegexCap
Version: 0.1
Summary: Replace packet fields with regex
Home-page: https://github.com/pocc/regexcap
Author: Ross Jacobs
Author-email: rj@swit.sh
License: Apache2
Platform: UNKNOWN
Classifier: License :: OSI Approved :: Apache Software License
Classifier: Programming Language :: Python :: 3
Classifier: Programming Language :: Python :: 3 :: Only
Classifier: Programming Language :: Python :: 3.6
Classifier: Programming Language :: Python :: 3.7
Classifier: Programming Language :: Python :: 3.8
Requires-Python: >=3.6.1
